ansible_runner_nats/__init__.py
ansible_runner_nats/config_parser.py
ansible_runner_nats/handlers.py
ansible_runner_nats/py.typed
ansible_runner_nats/service.py
ansible_runner_nats/tools.py
ansible_runner_nats-0.4.0.dist-info/LICENSE
ansible_runner_nats-0.4.0.dist-info/METADATA
ansible_runner_nats-0.4.0.dist-info/WHEEL
ansible_runner_nats-0.4.0.dist-info/entry_points.txt
ansible_runner_nats-0.4.0.dist-info/top_level.txt
ansible_runner_nats-0.4.0.dist-info/RECORD
