Metadata-Version: 2.1
Name: ansible-runner-nats
Version: 0.4.0
Summary: Ansible Runner NATS emitter
Author-email: guillaume.charbonnier@araymond.com
License: Apache-2.0
Project-URL: Repository, https://github.com/charbonnierg/ansible-runner-nats
Project-URL: Issues, https://github.com/charbonnierg/ansible-runner-nats/issues
Keywords: ansible,ansible-runner
Classifier: Programming Language :: Python :: 3
Classifier: License :: OSI Approved :: Apache Software License
Requires-Python: >=3.7
License-File: LICENSE
Requires-Dist: nats-py
Provides-Extra: ansible
Requires-Dist: ansible ; extra == 'ansible'
Provides-Extra: dev
Requires-Dist: black ; extra == 'dev'
Requires-Dist: isort ; extra == 'dev'
Requires-Dist: flake8 ; extra == 'dev'
Requires-Dist: mypy ; extra == 'dev'
Provides-Extra: nkeys
Requires-Dist: nats-py[nkeys] ; extra == 'nkeys'
Provides-Extra: tests
Requires-Dist: ansible-runner ; extra == 'tests'
Requires-Dist: pytest ; extra == 'tests'
Requires-Dist: pytest-cov ; extra == 'tests'
Requires-Dist: pytest-asyncio ; extra == 'tests'
Provides-Extra: websocket
Requires-Dist: aiohttp ; extra == 'websocket'
